Metadata-Version: 1.0
Name: dual-probability-byEmily
Version: 0.2
Summary: Gaussian and binomial distributions
Home-page: UNKNOWN
Author: Emily Xia
Author-email: UNKNOWN
License: UNKNOWN
Platform: UNKNOWN
